serialportlogger.py
PySerialPortLogger-2.0.0.dist-info/LICENSE
PySerialPortLogger-2.0.0.dist-info/METADATA
PySerialPortLogger-2.0.0.dist-info/WHEEL
PySerialPortLogger-2.0.0.dist-info/entry_points.txt
PySerialPortLogger-2.0.0.dist-info/top_level.txt
PySerialPortLogger-2.0.0.dist-info/RECORD
