Metadata-Version: 2.1
Name: PySerialPortLogger
Version: 2.0.0
Summary: An easy way to log output in a complex POSIX environment
Author-email: Steven Michaud <smichaud@pobox.com>
License: The MIT License (MIT)
Project-URL: Homepage, https://github.com/steven-michaud/PySerialPortLogger
Project-URL: Bug Tracker, https://github.com/steven-michaud/PySerialPortLogger/issues
Keywords: virtual serial port,virtual com port,logger,logging,python,POSIX
Classifier: Programming Language :: Python :: 3
Classifier: License :: OSI Approved :: MIT License
Classifier: Operating System :: POSIX
Classifier: Intended Audience :: Developers
Requires-Python: >=3.5
License-File: LICENSE
